src/defines.v
`ifndef DEFINES_V
`define DEFINES_V

// Opcodes
`define OPCODE_R_TYPE   7'b0110011
`define OPCODE_I_TYPE   7'b0010011
`define OPCODE_LOAD     7'b0000011
`define OPCODE_STORE    7'b0100011
`define OPCODE_BRANCH   7'b1100011
`define OPCODE_JAL      7'b1101111
`define OPCODE_JALR     7'b1100111
`define OPCODE_LUI      7'b0110111
`define OPCODE_AUIPC    7'b0010111

// ALU Operations
`define ALU_ADD  4'b0000
`define ALU_SUB  4'b0001
`define ALU_SLL  4'b0010
`define ALU_SLT  4'b0011
`define ALU_SLTU 4'b0100
`define ALU_XOR  4'b0101
`define ALU_SRL  4'b0110
`define ALU_SRA  4'b0111
`define ALU_OR   4'b1000
`define ALU_AND  4'b1001

`endif

src/data_memory.v
module data_memory (
    input wire clk,
    input wire wr_en,
    input wire [31:0] addr,
    input wire [31:0] wr_data,
    output wire [31:0] rd_data
);

    reg [31:0] mem [0:1023]; // 4KB data memory

    assign rd_data = mem[addr[11:2]];

    always @(posedge clk) begin
        if (wr_en) begin
            mem[addr[11:2]] <= wr_data;
        end
    end

endmodule

src/alu.v
`include "defines.v"

module alu (
    input wire [31:0] a,
    input wire [31:0] b,
    input wire [3:0] alu_ctrl,
    output reg [31:0] result,
    output wire zero
);

    always @(*) begin
        case (alu_ctrl)
            `ALU_ADD:  result = a + b;
            `ALU_SUB:  result = a - b;
            `ALU_SLL:  result = a << b[4:0];
            `ALU_SLT:  result = ($signed(a) < $signed(b)) ? 32'b1 : 32'b0;
            `ALU_SLTU: result = (a < b) ? 32'b1 : 32'b0;
            `ALU_XOR:  result = a ^ b;
            `ALU_SRL:  result = a >> b[4:0];
            `ALU_SRA:  result = $signed(a) >>> b[4:0];
            `ALU_OR:   result = a | b;
            `ALU_AND:  result = a & b;
            default:   result = 32'b0;
        endcase
    end

    assign zero = (result == 32'b0);

endmodule

src/imm_gen.v
`include "defines.v"

module imm_gen (
    input wire [31:0] inst,
    output reg [31:0] imm
);

    wire [6:0] opcode = inst[6:0];

    always @(*) begin
        case (opcode)
            `OPCODE_I_TYPE, `OPCODE_LOAD, `OPCODE_JALR: 
                imm = {{20{inst[31]}}, inst[31:20]};
            `OPCODE_STORE:
                imm = {{20{inst[31]}}, inst[31:25], inst[11:7]};
            `OPCODE_BRANCH:
                imm = {{20{inst[31]}}, inst[7], inst[30:25], inst[11:8], 1'b0};
            `OPCODE_LUI, `OPCODE_AUIPC: 
                imm = {inst[31:12], 12'b0};
            `OPCODE_JAL: 
                imm = {{12{inst[31]}}, inst[19:12], inst[20], inst[30:21], 1'b0};
            default: 
                imm = 32'b0;
        endcase
    end

endmodule

src/register_file.v
module register_file (
    input wire clk,
    input wire rst_n,
    input wire [4:0] rs1_addr,
    input wire [4:0] rs2_addr,
    input wire [4:0] rd_addr,
    input wire [31:0] wr_data,
    input wire wr_en,
    output wire [31:0] rs1_data,
    output wire [31:0] rs2_data
);

    reg [31:0] regs [0:31];
    integer i;

    // Read ports (asynchronous)
    assign rs1_data = (rs1_addr == 0) ? 32'b0 : regs[rs1_addr];
    assign rs2_data = (rs2_addr == 0) ? 32'b0 : regs[rs2_addr];

    // Write port (synchronous)
    always @(posedge clk or negedge rst_n) begin
        if (!rst_n) begin
            for (i = 0; i < 32; i = i + 1) begin
                regs[i] <= 32'b0;
            end
        end else if (wr_en && (rd_addr != 0)) begin
            regs[rd_addr] <= wr_data;
        end
    end

endmodule

src/control_unit.v
`include "defines.v"

module control_unit (
    input wire [6:0] opcode,
    input wire [2:0] funct3,
    input wire [6:0] funct7,
    output reg branch,
    output reg jump,
    output reg mem_read,
    output reg mem_write,
    output reg reg_write,
    output reg [1:0] alu_src_a, // 0: rs1, 1: pc
    output reg alu_src_b,       // 0: rs2, 1: imm
    output reg [3:0] alu_ctrl,
    output reg [1:0] result_src // 0: alu, 1: mem, 2: pc+4
);

    always @(*) begin
        // Defaults
        branch = 0;
        jump = 0;
        mem_read = 0;
        mem_write = 0;
        reg_write = 0;
        alu_src_a = 0;
        alu_src_b = 0;
        alu_ctrl = 0;
        result_src = 0;

        case (opcode)
            `OPCODE_R_TYPE: begin
                reg_write = 1;
                alu_src_b = 0;
                case (funct3)
                    3'b000: alu_ctrl = (funct7[5]) ? `ALU_SUB : `ALU_ADD;
                    3'b001: alu_ctrl = `ALU_SLL;
                    3'b010: alu_ctrl = `ALU_SLT;
                    3'b011: alu_ctrl = `ALU_SLTU;
                    3'b100: alu_ctrl = `ALU_XOR;
                    3'b101: alu_ctrl = (funct7[5]) ? `ALU_SRA : `ALU_SRL;
                    3'b110: alu_ctrl = `ALU_OR;
                    3'b111: alu_ctrl = `ALU_AND;
                endcase
            end
            `OPCODE_I_TYPE: begin
                reg_write = 1;
                alu_src_b = 1;
                case (funct3)
                    3'b000: alu_ctrl = `ALU_ADD;
                    3'b001: alu_ctrl = `ALU_SLL;
                    3'b010: alu_ctrl = `ALU_SLT;
                    3'b011: alu_ctrl = `ALU_SLTU;
                    3'b100: alu_ctrl = `ALU_XOR;
                    3'b101: alu_ctrl = (funct7[5]) ? `ALU_SRA : `ALU_SRL;
                    3'b110: alu_ctrl = `ALU_OR;
                    3'b111: alu_ctrl = `ALU_AND;
                endcase
            end
            `OPCODE_LOAD: begin
                reg_write = 1;
                mem_read = 1;
                alu_src_b = 1;
                alu_ctrl = `ALU_ADD;
                result_src = 1;
            end
            `OPCODE_STORE: begin
                mem_write = 1;
                alu_src_b = 1;
                alu_ctrl = `ALU_ADD;
            end
            `OPCODE_BRANCH: begin
                branch = 1;
                alu_src_b = 0;
                alu_ctrl = `ALU_SUB; // Comparison done via subtraction/flags
            end
            `OPCODE_JAL: begin
                jump = 1;
                reg_write = 1;
                alu_src_a = 1; // PC
                alu_src_b = 1; // Imm
                alu_ctrl = `ALU_ADD; // PC + Imm
                result_src = 2; // Store PC+4
            end
            `OPCODE_JALR: begin
                jump = 1;
                reg_write = 1;
                alu_src_a = 0; // rs1
                alu_src_b = 1; // Imm
                alu_ctrl = `ALU_ADD;
                result_src = 2;
            end
            `OPCODE_LUI: begin
                reg_write = 1;
                alu_src_b = 1;
                alu_ctrl = `ALU_ADD; // LUI is handled by imm_gen + add 0? No, usually just pass imm. 
                // Simplified: Treat as add x0, imm.
                // But LUI imm is shifted. imm_gen handles shift.
                // We need to add 0.
                // rs1 is x0 (0).
            end
            // ... other opcodes
        endcase
    end

endmodule

src/instruction_memory.v
module instruction_memory (
    input wire [31:0] addr,
    output wire [31:0] inst
);

    reg [31:0] mem [0:1023]; // 4KB instruction memory
    integer i;

    initial begin
        // Initialize with NOPs
        for (i = 0; i < 1024; i = i + 1) mem[i] = 32'b0;
        
        // Load program
        $readmemh("program.hex", mem);
    end

    // Word aligned access
    assign inst = mem[addr[11:2]];

endmodule

src/program_counter.v
module program_counter (
    input wire clk,
    input wire rst_n,
    input wire stall,
    input wire [31:0] next_pc,
    output reg [31:0] pc
);

    always @(posedge clk or negedge rst_n) begin
        if (!rst_n) begin
            pc <= 32'b0;
        end else if (!stall) begin
            pc <= next_pc;
        end
    end

endmodule

src/riscv_core.v
`include "defines.v"

module riscv_core (
    input wire clk,
    input wire rst_n,
    output wire [31:0] pc_out,
    output wire [31:0] alu_result_out
);

    // ===========================================================================
    // Internal Signals & Pipeline Registers
    // ===========================================================================

    // IF Stage
    wire [31:0] if_pc;
    wire [31:0] if_inst;
    wire [31:0] if_pc_plus_4;
    wire [31:0] next_pc;
    wire pc_src; // 0: PC+4, 1: Branch Target

    // IF/ID Pipeline Register
    reg [31:0] id_pc;
    reg [31:0] id_inst;
    reg [31:0] id_pc_plus_4;

    // ID Stage
    wire [6:0] id_opcode;
    wire [2:0] id_funct3;
    wire [6:0] id_funct7;
    wire [4:0] id_rs1_addr, id_rs2_addr, id_rd_addr;
    wire [31:0] id_rs1_data, id_rs2_data;
    wire [31:0] id_imm;
    wire id_branch, id_jump, id_mem_read, id_mem_write, id_reg_write, id_alu_src_b;
    wire [1:0] id_alu_src_a, id_result_src;
    wire [3:0] id_alu_ctrl;
    wire [31:0] id_branch_target;
    wire id_branch_taken;

    // ID/EX Pipeline Register
    reg [31:0] ex_pc;
    reg [31:0] ex_rs1_data, ex_rs2_data;
    reg [31:0] ex_imm;
    reg [4:0] ex_rs1_addr, ex_rs2_addr, ex_rd_addr;
    reg ex_reg_write, ex_mem_read, ex_mem_write, ex_alu_src_b;
    reg ex_branch, ex_jump; // Added missing declarations
    reg [1:0] ex_alu_src_a, ex_result_src;
    reg [3:0] ex_alu_ctrl;
    reg [31:0] ex_pc_plus_4;

    // EX Stage
    wire [31:0] ex_alu_in_a, ex_alu_in_b;
    wire [31:0] ex_alu_result;
    wire ex_zero;
    wire [31:0] ex_forward_a_val, ex_forward_b_val;

    // EX/MEM Pipeline Register
    reg [31:0] mem_alu_result;
    reg [31:0] mem_rs2_data; // For store
    reg [4:0] mem_rd_addr;
    reg mem_reg_write, mem_mem_read, mem_mem_write;
    reg [1:0] mem_result_src;
    reg [31:0] mem_pc_plus_4;

    // MEM Stage
    wire [31:0] mem_read_data;

    // MEM/WB Pipeline Register
    reg [31:0] wb_alu_result;
    reg [31:0] wb_read_data;
    reg [4:0] wb_rd_addr;
    reg wb_reg_write;
    reg [1:0] wb_result_src;
    reg [31:0] wb_pc_plus_4;

    // WB Stage
    reg [31:0] wb_write_data;

    // Hazard / Forwarding
    wire stall_if, stall_id;
    wire flush_id; // Not used for branches in delayed branching!
    wire [1:0] forward_a, forward_b;

    // ===========================================================================
    // IF Stage
    // ===========================================================================
    
    assign if_pc_plus_4 = if_pc + 4;
    
    // PC Mux
    // In delayed branching, if branch is taken in ID, we update PC to target.
    // The instruction currently in IF (Delay Slot) is allowed to proceed.
    assign next_pc = (pc_src) ? id_branch_target : if_pc_plus_4;

    program_counter pc_module (
        .clk(clk),
        .rst_n(rst_n),
        .stall(stall_if),
        .next_pc(next_pc),
        .pc(if_pc)
    );

    instruction_memory imem (
        .addr(if_pc),
        .inst(if_inst)
    );

    // IF/ID Register
    always @(posedge clk or negedge rst_n) begin
        if (!rst_n) begin
            id_pc <= 0;
            id_inst <= 0; // NOP
            id_pc_plus_4 <= 0;
        end else if (!stall_id) begin
            // No flush for branch! That's the delay slot feature.
            id_pc <= if_pc;
            id_inst <= if_inst;
            id_pc_plus_4 <= if_pc_plus_4;
        end
    end

    // ===========================================================================
    // ID Stage
    // ===========================================================================

    assign id_opcode = id_inst[6:0];
    assign id_rd_addr = id_inst[11:7];
    assign id_funct3 = id_inst[14:12];
    assign id_rs1_addr = id_inst[19:15];
    assign id_rs2_addr = id_inst[24:20];
    assign id_funct7 = id_inst[31:25];

    control_unit ctrl (
        .opcode(id_opcode),
        .funct3(id_funct3),
        .funct7(id_funct7),
        .branch(id_branch),
        .jump(id_jump),
        .mem_read(id_mem_read),
        .mem_write(id_mem_write),
        .reg_write(id_reg_write),
        .alu_src_a(id_alu_src_a),
        .alu_src_b(id_alu_src_b),
        .alu_ctrl(id_alu_ctrl),
        .result_src(id_result_src)
    );

    register_file regfile (
        .clk(clk),
        .rst_n(rst_n),
        .rs1_addr(id_rs1_addr),
        .rs2_addr(id_rs2_addr),
        .rd_addr(wb_rd_addr),
        .wr_data(wb_write_data),
        .wr_en(wb_reg_write),
        .rs1_data(id_rs1_data),
        .rs2_data(id_rs2_data)
    );

    imm_gen ig (
        .inst(id_inst),
        .imm(id_imm)
    );

    // Branch Logic (Resolve in ID)
    // Simple comparison for BEQ (using XOR result from ALU would be EX stage, 
    // but for ID resolution we need comparators here or assume simple equality)
    // For full RISC-V compliance we need full comparators. 
    // Let's implement simple equality check in ID for BEQ/BNE.
    // For BLT/BGE we need a subtractor.
    // To keep it simple and synthesizable, let's instantiate a comparator.
    
    wire [31:0] op_a = (forward_a == 2'b01) ? mem_alu_result : // Forwarding from MEM (not WB because WB writes in first half? No, standard forwarding)
                       (forward_a == 2'b10) ? wb_write_data : id_rs1_data; // Wait, forwarding logic is usually for EX stage.
                       // For ID stage branch resolution, we need to forward from EX and MEM stages if they write to rs1/rs2.
    
    // Simplified: We will assume the test code avoids data hazards for the branch condition itself 
    // or we implement full forwarding to ID.
    // Let's implement basic forwarding to ID for the branch comparator.
    
    wire [31:0] id_val_rs1 = (mem_rd_addr == id_rs1_addr && mem_reg_write && mem_rd_addr != 0) ? mem_alu_result :
                             (wb_rd_addr == id_rs1_addr && wb_reg_write && wb_rd_addr != 0) ? wb_write_data : id_rs1_data;
    wire [31:0] id_val_rs2 = (mem_rd_addr == id_rs2_addr && mem_reg_write && mem_rd_addr != 0) ? mem_alu_result :
                             (wb_rd_addr == id_rs2_addr && wb_reg_write && wb_rd_addr != 0) ? wb_write_data : id_rs2_data;

    wire branch_cond_met;
    assign branch_cond_met = (id_funct3 == 3'b000) ? (id_val_rs1 == id_val_rs2) : // BEQ
                             (id_funct3 == 3'b001) ? (id_val_rs1 != id_val_rs2) : // BNE
                             (id_funct3 == 3'b100) ? ($signed(id_val_rs1) < $signed(id_val_rs2)) : // BLT
                             (id_funct3 == 3'b101) ? ($signed(id_val_rs1) >= $signed(id_val_rs2)) : // BGE
                             0;

    assign id_branch_taken = (id_branch && branch_cond_met) || id_jump;
    assign id_branch_target = (id_jump && id_opcode == `OPCODE_JALR) ? (id_val_rs1 + id_imm) : (id_pc + id_imm);

    assign pc_src = id_branch_taken; // Controls PC Mux

    // ID/EX Register
    always @(posedge clk or negedge rst_n) begin
        if (!rst_n) begin
            ex_pc <= 0;
            ex_rs1_data <= 0;
            ex_rs2_data <= 0;
            ex_imm <= 0;
            ex_rs1_addr <= 0;
            ex_rs2_addr <= 0;
            ex_rd_addr <= 0;
            ex_reg_write <= 0;
            ex_mem_read <= 0;
            ex_mem_write <= 0;
            ex_alu_src_b <= 0;
            ex_alu_src_a <= 0;
            ex_result_src <= 0;
            ex_alu_ctrl <= 0;
            ex_pc_plus_4 <= 0;
        end else begin
            // If we stall (load-use hazard), we insert a bubble (NOP)
            if (stall_id) begin
                ex_reg_write <= 0;
                ex_mem_write <= 0;
                ex_mem_read <= 0;
                ex_branch <= 0;
                ex_jump <= 0;
            end else begin
                ex_pc <= id_pc;
                ex_rs1_data <= id_rs1_data;
                ex_rs2_data <= id_rs2_data;
                ex_imm <= id_imm;
                ex_rs1_addr <= id_rs1_addr;
                ex_rs2_addr <= id_rs2_addr;
                ex_rd_addr <= id_rd_addr;
                ex_reg_write <= id_reg_write;
                ex_mem_read <= id_mem_read;
                ex_mem_write <= id_mem_write;
                ex_branch <= id_branch;
                ex_jump <= id_jump;
                ex_alu_src_b <= id_alu_src_b;
                ex_alu_src_a <= id_alu_src_a;
                ex_result_src <= id_result_src;
                ex_alu_ctrl <= id_alu_ctrl;
                ex_pc_plus_4 <= id_pc_plus_4;
            end
        end
    end

    // ===========================================================================
    // EX Stage
    // ===========================================================================

    // Forwarding Logic for ALU
    assign forward_a = (mem_reg_write && (mem_rd_addr != 0) && (mem_rd_addr == ex_rs1_addr)) ? 2'b10 :
                       (wb_reg_write && (wb_rd_addr != 0) && (wb_rd_addr == ex_rs1_addr)) ? 2'b01 : 2'b00;
    
    assign forward_b = (mem_reg_write && (mem_rd_addr != 0) && (mem_rd_addr == ex_rs2_addr)) ? 2'b10 :
                       (wb_reg_write && (wb_rd_addr != 0) && (wb_rd_addr == ex_rs2_addr)) ? 2'b01 : 2'b00;

    assign ex_forward_a_val = (forward_a == 2'b10) ? mem_alu_result :
                              (forward_a == 2'b01) ? wb_write_data : ex_rs1_data;

    assign ex_forward_b_val = (forward_b == 2'b10) ? mem_alu_result :
                              (forward_b == 2'b01) ? wb_write_data : ex_rs2_data;

    assign ex_alu_in_a = (ex_alu_src_a == 1) ? ex_pc : ex_forward_a_val;
    assign ex_alu_in_b = (ex_alu_src_b == 1) ? ex_imm : ex_forward_b_val;

    alu alu_inst (
        .a(ex_alu_in_a),
        .b(ex_alu_in_b),
        .alu_ctrl(ex_alu_ctrl),
        .result(ex_alu_result),
        .zero(ex_zero)
    );

    // EX/MEM Register
    always @(posedge clk or negedge rst_n) begin
        if (!rst_n) begin
            mem_alu_result <= 0;
            mem_rs2_data <= 0;
            mem_rd_addr <= 0;
            mem_reg_write <= 0;
            mem_mem_read <= 0;
            mem_mem_write <= 0;
            mem_result_src <= 0;
            mem_pc_plus_4 <= 0;
        end else begin
            mem_alu_result <= ex_alu_result;
            mem_rs2_data <= ex_forward_b_val; // Store data needs forwarding too
            mem_rd_addr <= ex_rd_addr;
            mem_reg_write <= ex_reg_write;
            mem_mem_read <= ex_mem_read;
            mem_mem_write <= ex_mem_write;
            mem_result_src <= ex_result_src;
            mem_pc_plus_4 <= ex_pc_plus_4;
        end
    end

    // ===========================================================================
    // MEM Stage
    // ===========================================================================

    data_memory dmem (
        .clk(clk),
        .wr_en(mem_mem_write),
        .addr(mem_alu_result),
        .wr_data(mem_rs2_data),
        .rd_data(mem_read_data)
    );

    // MEM/WB Register
    always @(posedge clk or negedge rst_n) begin
        if (!rst_n) begin
            wb_alu_result <= 0;
            wb_read_data <= 0;
            wb_rd_addr <= 0;
            wb_reg_write <= 0;
            wb_result_src <= 0;
            wb_pc_plus_4 <= 0;
        end else begin
            wb_alu_result <= mem_alu_result;
            wb_read_data <= mem_read_data;
            wb_rd_addr <= mem_rd_addr;
            wb_reg_write <= mem_reg_write;
            wb_result_src <= mem_result_src;
            wb_pc_plus_4 <= mem_pc_plus_4;
        end
    end

    // ===========================================================================
    // WB Stage
    // ===========================================================================

    always @(*) begin
        case (wb_result_src)
            0: wb_write_data = wb_alu_result;
            1: wb_write_data = wb_read_data;
            2: wb_write_data = wb_pc_plus_4;
            default: wb_write_data = 0;
        endcase
    end

    // Hazard Detection Unit (Load-Use)
    // If ID stage uses a register that EX stage is loading from memory, stall.
    // Also stall if Branch in ID depends on EX stage result (ALU or Load)
    wire load_use_hazard = (ex_mem_read && ((ex_rd_addr == id_rs1_addr) || (ex_rd_addr == id_rs2_addr)));
    
    wire branch_hazard = (id_branch && (
        (ex_reg_write && ex_rd_addr != 0 && (ex_rd_addr == id_rs1_addr || ex_rd_addr == id_rs2_addr)) ||
        (mem_mem_read && mem_rd_addr != 0 && (mem_rd_addr == id_rs1_addr || mem_rd_addr == id_rs2_addr))
    ));

    assign stall_id = load_use_hazard || branch_hazard;
    assign stall_if = stall_id;

    // Outputs for testbench
    assign pc_out = if_pc;
    assign alu_result_out = ex_alu_result;

endmodule

test/tb_riscv.v
`timescale 1ns / 1ps

module tb_riscv;

    reg clk;
    reg rst_n;
    wire [31:0] pc_out;
    wire [31:0] alu_result_out;

    // Instantiate the Core
    riscv_core core (
        .clk(clk),
        .rst_n(rst_n),
        .pc_out(pc_out),
        .alu_result_out(alu_result_out)
    );

    // Clock Generation
    initial begin
        clk = 0;
        forever #5 clk = ~clk;
    end

    // Test Sequence
    initial begin
        // Initialize
        rst_n = 0;
        #20;
        rst_n = 1;

        // Run simulation
        #500;
        
        // Print Register File State
        $display("\nFinal Register State:");
        $display("x1 (10) = %d", core.regfile.regs[1]);
        $display("x2 (20) = %d", core.regfile.regs[2]);
        $display("x3 (5)  = %d  <-- Delay Slot Executed!", core.regfile.regs[3]);
        $display("x4 (0)  = %d  <-- Skipped Instruction!", core.regfile.regs[4]);
        $display("x5 (30) = %d  <-- Branch Target Reached!", core.regfile.regs[5]);

        $finish;
    end

    // Monitor
    initial begin
        $monitor("Time=%0t | PC=%h | ALU_Res=%h", $time, pc_out, alu_result_out);
    end

    // Waveform dump
    initial begin
        $dumpfile("riscv_core.vcd");
        $dumpvars(0, tb_riscv);
    end

endmodule

riscv_core.vcd
$date
	Wed Nov 19 22:37:29 2025
$end
$version
	Icarus Verilog
$end
$timescale
	1ps
$end
$scope module tb_riscv $end
$var wire 32 ! pc_out [31:0] $end
$var wire 32 " alu_result_out [31:0] $end
$var reg 1 # clk $end
$var reg 1 $ rst_n $end
$scope module core $end
$var wire 32 % alu_result_out [31:0] $end
$var wire 1 & branch_hazard $end
$var wire 1 # clk $end
$var wire 1 ' id_branch_taken $end
$var wire 1 ( load_use_hazard $end
$var wire 32 ) pc_out [31:0] $end
$var wire 1 * pc_src $end
$var wire 1 $ rst_n $end
$var wire 1 + stall_id $end
$var wire 1 , stall_if $end
$var wire 32 - op_a [31:0] $end
$var wire 32 . next_pc [31:0] $end
$var wire 32 / mem_read_data [31:0] $end
$var wire 32 0 if_pc_plus_4 [31:0] $end
$var wire 32 1 if_pc [31:0] $end
$var wire 32 2 if_inst [31:0] $end
$var wire 32 3 id_val_rs2 [31:0] $end
$var wire 32 4 id_val_rs1 [31:0] $end
$var wire 32 5 id_rs2_data [31:0] $end
$var wire 5 6 id_rs2_addr [4:0] $end
$var wire 32 7 id_rs1_data [31:0] $end
$var wire 5 8 id_rs1_addr [4:0] $end
$var wire 2 9 id_result_src [1:0] $end
$var wire 1 : id_reg_write $end
$var wire 5 ; id_rd_addr [4:0] $end
$var wire 7 < id_opcode [6:0] $end
$var wire 1 = id_mem_write $end
$var wire 1 > id_mem_read $end
$var wire 1 ? id_jump $end
$var wire 32 @ id_imm [31:0] $end
$var wire 7 A id_funct7 [6:0] $end
$var wire 3 B id_funct3 [2:0] $end
$var wire 32 C id_branch_target [31:0] $end
$var wire 1 D id_branch $end
$var wire 1 E id_alu_src_b $end
$var wire 2 F id_alu_src_a [1:0] $end
$var wire 4 G id_alu_ctrl [3:0] $end
$var wire 2 H forward_b [1:0] $end
$var wire 2 I forward_a [1:0] $end
$var wire 1 J ex_zero $end
$var wire 32 K ex_forward_b_val [31:0] $end
$var wire 32 L ex_forward_a_val [31:0] $end
$var wire 32 M ex_alu_result [31:0] $end
$var wire 32 N ex_alu_in_b [31:0] $end
$var wire 32 O ex_alu_in_a [31:0] $end
$var wire 1 P branch_cond_met $end
$var reg 4 Q ex_alu_ctrl [3:0] $end
$var reg 2 R ex_alu_src_a [1:0] $end
$var reg 1 S ex_alu_src_b $end
$var reg 1 T ex_branch $end
$var reg 32 U ex_imm [31:0] $end
$var reg 1 V ex_jump $end
$var reg 1 W ex_mem_read $end
$var reg 1 X ex_mem_write $end
$var reg 32 Y ex_pc [31:0] $end
$var reg 32 Z ex_pc_plus_4 [31:0] $end
$var reg 5 [ ex_rd_addr [4:0] $end
$var reg 1 \ ex_reg_write $end
$var reg 2 ] ex_result_src [1:0] $end
$var reg 5 ^ ex_rs1_addr [4:0] $end
$var reg 32 _ ex_rs1_data [31:0] $end
$var reg 5 ` ex_rs2_addr [4:0] $end
$var reg 32 a ex_rs2_data [31:0] $end
$var reg 32 b id_inst [31:0] $end
$var reg 32 c id_pc [31:0] $end
$var reg 32 d id_pc_plus_4 [31:0] $end
$var reg 32 e mem_alu_result [31:0] $end
$var reg 1 f mem_mem_read $end
$var reg 1 g mem_mem_write $end
$var reg 32 h mem_pc_plus_4 [31:0] $end
$var reg 5 i mem_rd_addr [4:0] $end
$var reg 1 j mem_reg_write $end
$var reg 2 k mem_result_src [1:0] $end
$var reg 32 l mem_rs2_data [31:0] $end
$var reg 32 m wb_alu_result [31:0] $end
$var reg 32 n wb_pc_plus_4 [31:0] $end
$var reg 5 o wb_rd_addr [4:0] $end
$var reg 32 p wb_read_data [31:0] $end
$var reg 1 q wb_reg_write $end
$var reg 2 r wb_result_src [1:0] $end
$var reg 32 s wb_write_data [31:0] $end
$scope module alu_inst $end
$var wire 32 t a [31:0] $end
$var wire 4 u alu_ctrl [3:0] $end
$var wire 32 v b [31:0] $end
$var wire 1 J zero $end
$var reg 32 w result [31:0] $end
$upscope $end
$scope module ctrl $end
$var wire 3 x funct3 [2:0] $end
$var wire 7 y funct7 [6:0] $end
$var wire 7 z opcode [6:0] $end
$var reg 4 { alu_ctrl [3:0] $end
$var reg 2 | alu_src_a [1:0] $end
$var reg 1 E alu_src_b $end
$var reg 1 D branch $end
$var reg 1 ? jump $end
$var reg 1 > mem_read $end
$var reg 1 = mem_write $end
$var reg 1 : reg_write $end
$var reg 2 } result_src [1:0] $end
$upscope $end
$scope module dmem $end
$var wire 32 ~ addr [31:0] $end
$var wire 1 # clk $end
$var wire 32 !" rd_data [31:0] $end
$var wire 32 "" wr_data [31:0] $end
$var wire 1 g wr_en $end
$upscope $end
$scope module ig $end
$var wire 32 #" inst [31:0] $end
$var wire 7 $" opcode [6:0] $end
$var reg 32 %" imm [31:0] $end
$upscope $end
$scope module imem $end
$var wire 32 &" inst [31:0] $end
$var wire 32 '" addr [31:0] $end
$var integer 32 (" i [31:0] $end
$upscope $end
$scope module pc_module $end
$var wire 1 # clk $end
$var wire 32 )" next_pc [31:0] $end
$var wire 1 $ rst_n $end
$var wire 1 , stall $end
$var reg 32 *" pc [31:0] $end
$upscope $end
$scope module regfile $end
$var wire 1 # clk $end
$var wire 5 +" rd_addr [4:0] $end
$var wire 5 ," rs1_addr [4:0] $end
$var wire 5 -" rs2_addr [4:0] $end
$var wire 1 $ rst_n $end
$var wire 32 ." wr_data [31:0] $end
$var wire 1 q wr_en $end
$var wire 32 /" rs2_data [31:0] $end
$var wire 32 0" rs1_data [31:0] $end
$var integer 32 1" i [31:0] $end
$upscope $end
$upscope $end
$upscope $end
$enddefinitions $end
$comment Show the parameter values. $end
$dumpall
$end
#0
$dumpvars
b100000 1"
b0 0"
b0 /"
b0 ."
b0 -"
b0 ,"
b0 +"
b0 *"
b100 )"
b10000000000 ("
b0 '"
b101000000000000010010011 &"
b0 %"
b0 $"
b0 #"
b0 ""
bx !"
b0 ~
b0 }
b0 |
b0 {
b0 z
b0 y
b0 x
b0 w
b0 v
b0 u
b0 t
b0 s
b0 r
0q
b0 p
b0 o
b0 n
b0 m
b0 l
b0 k
0j
b0 i
b0 h
0g
0f
b0 e
b0 d
b0 c
b0 b
b0 a
b0 `
b0 _
b0 ^
b0 ]
0\
b0 [
b0 Z
b0 Y
0X
0W
xV
b0 U
xT
0S
b0 R
b0 Q
1P
b0 O
b0 N
b0 M
b0 L
b0 K
1J
b0 I
b0 H
b0 G
b0 F
0E
0D
b0 C
b0 B
b0 A
b0 @
0?
0>
0=
b0 <
b0 ;
0:
b0 9
b0 8
b0 7
b0 6
b0 5
b0 4
b0 3
b101000000000000010010011 2
b0 1
b100 0
bx /
b100 .
b0 -
0,
0+
0*
b0 )
0(
0'
0&
b0 %
0$
0#
b0 "
b0 !
$end
#5000
b100000 1"
1#
#10000
0#
#15000
b100000 1"
1#
#20000
0#
1$
#25000
1E
1:
b1010 C
b10011 <
b10011 z
b1 ;
b1010 6
b1010 -"
b1010 @
b1010 %"
b10011 $"
b1010000000000000100010011 2
b1010000000000000100010011 &"
b1000 .
b1000 )"
bx p
0V
0T
b100 d
b101000000000000010010011 b
b101000000000000010010011 #"
b1000 0
b100 !
b100 )
b100 1
b100 '"
b100 *"
1#
#30000
0#
#35000
0J
b1010 "
b1010 %
b1010 M
b1010 w
b100001000011001100011 2
b100001000011001100011 &"
b1100 .
b1100 )"
b10 ;
b10100 6
b10100 -"
b10100 @
b10100 %"
b11000 C
b1010 N
b1010 v
b1100 0
b1000 !
b1000 )
b1000 1
b1000 '"
b1000 *"
b1000 d
b1010000000000000100010011 b
b1010000000000000100010011 #"
b100 c
b100 Z
1S
1\
b1 [
b1010 `
b1010 U
1#
#40000
0#
#45000
1*
1'
b1010 3
b1010 4
b10100 "
b10100 %
b10100 M
b10100 w
b1 G
b1 {
1D
0E
0:
b10100 N
b10100 v
b1100011 <
b1100011 z
b1100 ;
b1 8
b1 ,"
b1 6
b1 -"
b1100 @
b1100 %"
b1100011 $"
b10100 C
b10100000000000110010011 2
b10100000000000110010011 &"
b10100 .
b10100 )"
b100 h
1j
b1 i
b1010 e
b1010 ~
b1000 Z
b10 [
b10100 `
b10100 U
b100 Y
b1100 d
b100001000011001100011 b
b100001000011001100011 #"
b1000 c
b10000 0
b1100 !
b1100 )
b1100 1
b1100 '"
b1100 *"
1#
#50000
0#
#55000
b1010 O
b1010 t
b1010 L
b1010 K
b10100 -
0*
0'
b1 I
b1 H
1E
1:
b0 G
b0 {
0D
b11000 .
b11000 )"
b1111000000000001010010011 2
b1111000000000001010010011 &"
b10011 <
b10011 z
b11 ;
b0 8
b0 ,"
b101 6
b101 -"
b101 @
b101 %"
b10011 $"
b10001 C
1J
b0 "
b0 %
b0 M
b0 w
b1010 N
b1010 v
b0 4
b0 3
b1010 s
b1010 ."
b11000 0
b10100 !
b10100 )
b10100 1
b10100 '"
b10100 *"
b10000 d
b10100000000000110010011 b
b10100000000000110010011 #"
b1100 c
b1100 Z
b1 Q
b1 u
0S
1T
0\
b1100 [
b1 `
b1 ^
b1100 U
b1000 Y
b1000 h
b10 i
b10100 e
b10100 ~
b100 n
1q
b1 o
b1 +"
b1010 m
1#
#60000
0#
#65000
b0 O
b0 t
b0 L
b0 K
b0 H
b0 I
b10100 s
b10100 ."
b0 -
0J
b101 "
b101 %
b101 M
b101 w
b101 N
b101 v
b101 ;
b11110 6
b11110 -"
b11110 @
b11110 %"
b110010 C
b0 2
b0 &"
b11100 .
b11100 )"
b1000 n
b10 o
b10 +"
b10100 m
b1100 h
0j
b1100 i
b1010 l
b1010 ""
b0 e
b0 ~
b10000 Z
b0 Q
b0 u
1S
0T
1\
b11 [
b101 `
b0 ^
b101 U
b1100 Y
b11000 d
b1111000000000001010010011 b
b1111000000000001010010011 #"
b10100 c
b11100 0
b11000 !
b11000 )
b11000 1
b11000 '"
b11000 *"
1#
#70000
0#
